pg_runner/__init__.py
pg_runner/cli.py
pg_runner-0.1.3.dist-info/METADATA
pg_runner-0.1.3.dist-info/WHEEL
pg_runner-0.1.3.dist-info/entry_points.txt
pg_runner-0.1.3.dist-info/RECORD
