Metadata-Version: 2.3
Name: pg-runner
Version: 0.1.3
Summary: Standalone PostgreSQL database setup and SQL runner with phase and directory modes
License: MIT
Keywords: postgresql,sql,sqlalchemy,cli,devops,database
Author: khodaparastan
Author-email: mohammad@khodaparastan.com
Requires-Python: >=3.13
Classifier: Development Status :: 4 - Beta
Classifier: Environment :: Console
Classifier: Intended Audience :: Developers
Classifier: Intended Audience :: Information Technology
Classifier: License :: OSI Approved :: MIT License
Classifier: Operating System :: OS Independent
Classifier: Programming Language :: Python :: 3
Classifier: Programming Language :: Python :: 3 :: Only
Classifier: Programming Language :: Python :: 3.13
Classifier: Topic :: Database
Classifier: Topic :: System :: Systems Administration
Classifier: Topic :: Utilities
Requires-Dist: SQLAlchemy (>=2.0,<3.0)
Requires-Dist: psycopg2-binary (>=2.9.10,<3.0.0)
Project-URL: Homepage, https://github.com/khodaparastan/pg-runner
Project-URL: Repository, https://github.com/khodaparastan/pg-runner
